{"cameraMode":{"drawMode":0,"name":"Shaded","section":"Shading Mode"},"sceneLighting":true,"audioPlay":false,"sceneViewState":{"showFog":true,"showMaterialUpdate":false,"showSkybox":true,"showFlares":true,"showImageEffects":true,"showParticleSystems":true},"in2DMode":false,"pivot":{"x":1.8235807418823243,"y":2.730029821395874,"z":-1.2978124618530274},"rotation":{"x":0.027177980169653894,"y":-0.9412519335746765,"z":0.07812268286943436,"w":0.32744839787483218},"size":4.433107852935791,"orthographic":false}